{
  "pre_workout": [
    {
      "name": "Full Body Warm-Up",
      "duration": "5 min",
      "url": "https://www.youtube.com/embed/OcPs3x1vX1A"
    },
    {
      "name": "Dynamic Stretching Routine",
      "duration": "4 min",
      "url": "https://www.youtube.com/embed/2L2lnxIcNmo"
    },
    {
      "name": "5-Minute Warm-Up",
      "duration": "5 min",
      "url": "https://www.youtube.com/embed/R0mMyV5OtcM"
    }
  ],
  "post_workout": [
    {
      "name": "Cool Down Stretch",
      "duration": "5 min",
      "url": "https://www.youtube.com/embed/v7AYKMP6rOE"
    },
    {
      "name": "Post Workout Stretch",
      "duration": "10 min",
      "url": "https://www.youtube.com/embed/jeNwE4VXqgs"
    },
    {
      "name": "Static Stretching Routine",
      "duration": "6 min",
      "url": "https://www.youtube.com/embed/sTANio_2E0Q"
    }
  ]
}